{
  "$schema": "http://json-schema.org/draft-07/schema",
  "type": "object",
  "$id": "http://example.com/example.json",
  "required": ["firstName"],
  "properties": {
    "address": {
      "type": "string"
    },
    "gender": {
      "type": "string",
      "oneOf": [
        {
          "const": "MALE",
          "title": "Male"
        },
        {
          "const": "FEMALE",
          "title": "Female"
        },
        {
          "const": "UNDISCLOSED",
          "title": "Undisclosed"
        }
      ]
    },
    "firstName": {
      "type": "string",
      "minLength": 2,
      "maxLength": 20
    },
    "lastName": {
      "type": "string",
      "minLength": 5,
      "maxLength": 15
    }
  }
}
